<?xml version="1.0" encoding="utf-8"?>
<entry xmlns="http://www.w3.org/2005/Atom" xmlns:default="http://php.net/ns/news">
  <title>ConFoo Montreal: Early Bird Ending</title>
  <id>http://php.net/archive/2017.php#id2017-01-17-1</id>
  <published>2017-01-17T15:23:38-05:00</published>
  <updated>2017-01-17T15:23:38-05:00</updated>
  <default:finalTeaserDate xmlns="http://php.net/ns/news">2017-03-08</default:finalTeaserDate>
  <category term="conferences" label="Conference announcement"/>
  <link href="http://php.net/conferences/index.php#id2017-01-17-1" rel="alternate" type="text/html"/>
  <default:newsImage xmlns="http://php.net/ns/news" link="https://confoo.ca/en/yul2017" title="ConFoo Montreal 2017 (Mar 8-10) &amp; Vancouver 2017 (Dec 4-6)">confoo-yul2017-yvr2017.jpg</default:newsImage>
  <link href="https://confoo.ca/en/yul2017" rel="via" type="text/html"/>
  <content type="xhtml">
    <div xmlns="http://www.w3.org/1999/xhtml">
     <p>You can save on <a href="https://confoo.ca/en/yul2017">ConFoo Montreal</a> tickets until January 20, 2017. This huge conference will be held on March 8-10, 2017 and will feature over 150 <a href="https://confoo.ca/en/yul2017/sessions">presentations</a>.</p>
     
     <p>There is a great range of topics, including PHP, many other programming languages, databases, security, performance, machine learning and project management.</p>

     <p>We also just confirmed the dates for the next <a href="https://confoo.ca/en/yvr2017">ConFoo Vancouver</a>, which is scheduled for December 4-6, 2017.</p>
    </div>
  </content>
</entry>
